{
  "name": "Merfolk (Zendikar) (Ula Creed)",
  "size": "M",
  "speed": "30",
  "ability": "Cha 1, Int 2",
  "proficiency": "Survival",
  "spellAbility": "Intelligence",
  "trait": [
    {
      "name": "Description",
      "text": "Source: Plane Shift: Zendikar p. 13"
    },
    {
      "name": "Cantrip",
      "text": "You know one cantrip of your choice from the wizard spell list. Intelligence is your spellcasting ability for it.\n"
    },
    {
      "name": "Water Creed Navigation",
      "text": "You have proficiency with navigator's tools and in the Survival skill.\n"
    },
    {
      "name": "Age",
      "text": "Merfolk mature at the same rate humans do and reach adulthood around the age of 20. They live considerably longer than humans, though, often reaching well over 100 years.\n"
    },
    {
      "name": "Alignment",
      "text": "Most merfolk are neutral, though merfolk of the Emeria and Cosi creeds have chaotic leanings.\n"
    },
    {
      "name": "Amphibious",
      "text": "You can breathe air and water.\n"
    },
    {
      "name": "Size",
      "text": "Merfolk are about the same size and build as humans. Your size is Medium.\n"
    },
    {
      "name": "Swimming",
      "text": "You have a swimming speed of 30 feet.\n"
    },
    {
      "name": "Languages",
      "text": "You can speak, read, and write Common, Merfolk, and one extra language of your choice.\n"
    }
  ]
}